dynamic_models/__init__.py
dynamic_models/apps.py
dynamic_models/exceptions.py
dynamic_models/factory.py
dynamic_models/models.py
dynamic_models/schema.py
dynamic_models/utils.py
django_dynamic_model-0.1.0.dist-info/LICENSE
django_dynamic_model-0.1.0.dist-info/METADATA
django_dynamic_model-0.1.0.dist-info/WHEEL
django_dynamic_model-0.1.0.dist-info/top_level.txt
django_dynamic_model-0.1.0.dist-info/RECORD
