Metadata-Version: 2.1
Name: django-dynamic-model
Version: 0.1.0
Summary: Allow dynamic creation and updates to database schema at runtime.
Home-page: http://github.com/rvinzent/django-dynamic-models
Author: Ryan Vinzent
Author-email: rvinzent217@hotmail.com
License: MIT
Platform: UNKNOWN
Classifier: Intended Audience :: Developers
Classifier: License :: OSI Approved :: MIT License
Classifier: Operating System :: OS Independent
Classifier: Programming Language :: Python :: 3
Classifier: Programming Language :: Python :: 3.7
Classifier: Framework :: Django
